MANIFEST.in
README.rst
setup.py
django_webpacker/__init__.py
django_webpacker.egg-info/PKG-INFO
django_webpacker.egg-info/SOURCES.txt
django_webpacker.egg-info/dependency_links.txt
django_webpacker.egg-info/requires.txt
django_webpacker.egg-info/top_level.txt
django_webpacker/management/__init__.py
django_webpacker/management/commands/compress_css_js_files.py
docs/__init__.py